hattifnatt.py
hattifnatt-0.2.1.dist-info/LICENSE
hattifnatt-0.2.1.dist-info/METADATA
hattifnatt-0.2.1.dist-info/WHEEL
hattifnatt-0.2.1.dist-info/entry_points.txt
hattifnatt-0.2.1.dist-info/top_level.txt
hattifnatt-0.2.1.dist-info/RECORD
