Metadata-Version: 2.1
Name: hattifnatt
Version: 0.2.1
Summary: Push directory to Telegram channel
Home-page: https://github.com/alexshpilkin/hattifnatt
Author: Alexander Shpilkin
Author-email: ashpilkin@gmail.com
License: UNKNOWN
Platform: UNKNOWN
Classifier: Development Status :: 4 - Beta
Classifier: Intended Audience :: End Users/Desktop
Classifier: License :: CC0 1.0 Universal (CC0 1.0) Public Domain Dedication
Classifier: Operating System :: OS Independent
Classifier: Programming Language :: Python
Classifier: Programming Language :: Python :: 3
Classifier: Programming Language :: Python :: 3.5
Classifier: Programming Language :: Python :: 3.6
Classifier: Programming Language :: Python :: 3.7
Classifier: Topic :: Communications :: Chat
Classifier: Topic :: Communications :: File Sharing
Classifier: Topic :: Software Development :: Libraries :: Python Modules
Classifier: Topic :: Utilities
Requires-Python: >=3.5, <4
Requires-Dist: pathtools (>=0.1.2)
Requires-Dist: python-telegram-bot (<12,>=10.0.2)
Requires-Dist: watchdog (>=0.9.0)
